{
  "mislam0525@gmail.com": {
    "email": "mislam0525@gmail.com",
    "password": "asd",
    "fname": "Muhammad",
    "lname": "Islam",
    "address": "57-26 73rd St",
    "zip": "11378",
    "state": "NY",
    "lplate": "asd",
    "cmake": "asd",
    "cmodel": "asd",
    "cyear": "asd",
    "balance": 0
  },
  "admin@admin.com": {
    "email": "admin@admin.com",
    "password": "qwe",
    "fname": "admin",
    "lname": "admin",
    "address": "admin",
    "zip": "12345",
    "state": "KY",
    "lplate": "123",
    "cmake": "123",
    "cmodel": "123",
    "cyear": "123",
    "balance": 0
  }
}